{
  "slug": "AngelGrain",
  "name": "AngelGrain",
  "version": "2.0.0",
  "license": "proprietary",
  "brand": "VCVRack Freedom (BETA)",
  "author": "VCVRack Freedom",
  "authorEmail": "",
  "authorUrl": "",
  "pluginUrl": "",
  "manualUrl": "",
  "sourceUrl": "",
  "donateUrl": "",
  "changelogUrl": "",
  "modules": [
    {
      "slug": "AngelGrain",
      "name": "Angel Grain",
      "description": "32-voice granular delay with chaos, character, and pitch quantization",
      "tags": [
        "Effect",
        "Granular",
        "Delay"
      ]
    }
  ]
}
